swag/__init__.py
swag/camvid.py
swag/data.py
swag/losses.py
swag/utils.py
swag/models/__init__.py
swag/models/joint_transforms.py
swag/models/layers.py
swag/models/lenet5.py
swag/models/preresnet.py
swag/models/preresnet_dropout.py
swag/models/tiramisu.py
swag/models/vgg.py
swag/models/vgg_dropout.py
swag/models/wide_resnet.py
swag/models/wide_resnet_dropout.py
swag/posteriors/__init__.py
swag/posteriors/diag_laplace.py
swag/posteriors/laplace.py
swag/posteriors/swag.py
swa_gaussian-0.1.9.dist-info/LICENSE
swa_gaussian-0.1.9.dist-info/METADATA
swa_gaussian-0.1.9.dist-info/WHEEL
swa_gaussian-0.1.9.dist-info/top_level.txt
swa_gaussian-0.1.9.dist-info/RECORD
