Metadata-Version: 2.2
Name: swa_gaussian
Version: 0.1.9
Summary: SWA-Gaussian repo
Home-page: https://github.com/Helsinki-NLP/swa_gaussian
Author: Wesley Maddox, Timur Garipov, Pavel Izmailov, Dmitry Vetrov, Andrew Gordon Wilson
Author-email: wm326@cornell.edu
Maintainer: Sami Virpioja
Maintainer-email: sami.virpioja@helsinki.fi
License: BSD
Classifier: Development Status :: 3 - Alpha
Classifier: Intended Audience :: Science/Research
Classifier: Programming Language :: Python :: 3.6
Requires-Python: >=3.6
License-File: LICENSE
Requires-Dist: tqdm>=4.26.0
Requires-Dist: numpy>=1.14.3
Requires-Dist: torchvision>=0.2.1
Requires-Dist: gpytorch<1.14.0,>=0.1.0rc4
Requires-Dist: tabulate>=0.8.2
Requires-Dist: scipy>=1.1.0
Requires-Dist: setuptools>=39.1.0
Requires-Dist: matplotlib>=2.2.2
Requires-Dist: torch>=1.0.0
Requires-Dist: Pillow>=5.4.1
Requires-Dist: scikit_learn>=0.20.2
Dynamic: author
Dynamic: author-email
Dynamic: classifier
Dynamic: home-page
Dynamic: license
Dynamic: maintainer
Dynamic: maintainer-email
Dynamic: requires-dist
Dynamic: requires-python
Dynamic: summary
